{
 "creation": "2021-01-06 03:55:36.875381",
 "doctype": "DocType",
 "editable_grid": 1,
 "engine": "InnoDB",
 "field_order": [
  "attachment_type",
  "reference_type",
  "attachment_count",
  "column_break_3",
  "reference_no",
  "reference_date",
  "notes"
 ],
 "fields": [
  {
   "fieldname": "attachment_type",
   "fieldtype": "Attach",
   "in_list_view": 1,
   "label": "Attachment Type",
   "reqd": 1
  },
  {
   "fieldname": "reference_type",
   "fieldtype": "Select",
   "in_list_view": 1,
   "label": "Reference Type",
   "options": "\nImage\nVideo\nPaper"
  },
  {
   "fieldname": "column_break_3",
   "fieldtype": "Column Break"
  },
  {
   "fieldname": "reference_no",
   "fieldtype": "Data",
   "in_list_view": 1,
   "label": "Reference No"
  },
  {
   "fieldname": "reference_date",
   "fieldtype": "Date",
   "in_list_view": 1,
   "label": "Reference Date"
  },
  {
   "fieldname": "notes",
   "fieldtype": "Small Text",
   "label": "Notes"
  },
  {
   "default": "1",
   "fieldname": "attachment_count",
   "fieldtype": "Int",
   "in_list_view": 1,
   "label": "Attachment Count",
   "reqd": 1
  }
 ],
 "istable": 1,
 "modified": "2021-04-18 12:29:02.942328",
 "modified_by": "Administrator",
 "module": "Administrative Communication",
 "name": "Administrative Transaction Attachments",
 "owner": "Administrator",
 "permissions": [],
 "quick_entry": 1,
 "sort_field": "modified",
 "sort_order": "DESC",
 "track_changes": 1
}